sanic_rest/__init__.py
sanic_rest/exceptions.py
sanic_rest/protected_views.py
sanic_rest/views.py
sanic_rest-1.9.0.dist-info/LICENSE.md
sanic_rest-1.9.0.dist-info/METADATA
sanic_rest-1.9.0.dist-info/WHEEL
sanic_rest-1.9.0.dist-info/RECORD
