Metadata-Version: 2.1
Name: sanic-rest
Version: 1.9.0
Summary: Sanic Rest Framework with Google Cloud Datastore
Home-page: https://github.com/flamingo-run/sanic-rest
Keywords: sanic,restful,datastore
Author: Joao Daher
Author-email: joao@daher.dev
Requires-Python: >=3.11,<3.13
Classifier: Programming Language :: Python :: 3
Classifier: Programming Language :: Python :: 3.11
Classifier: Programming Language :: Python :: 3.12
Provides-Extra: auth
Requires-Dist: argon2_cffi ; extra == "auth"
Requires-Dist: gcp-pilot[datastore,storage]
Requires-Dist: passlib ; extra == "auth"
Requires-Dist: sanic
Requires-Dist: sanic-jwt ; extra == "auth"
Requires-Dist: sanic-openapi
Project-URL: Repository, https://github.com/flamingo-run/sanic-rest
